pyaascan/__init__.py
pyaascan/bio_utils.py
pyaascan/cli.py
pyaascan/codon_utils.py
pyaascan/primer_design.py
pyaascan/primer_format.py
pyaascan-0.1.0.dist-info/METADATA
pyaascan-0.1.0.dist-info/WHEEL
pyaascan-0.1.0.dist-info/entry_points.txt
pyaascan-0.1.0.dist-info/RECORD
