Metadata-Version: 2.4
Name: pyaascan
Version: 0.1.0
Summary: A python implementation of AAscan
Author-email: deepthought <deepthough@postech.ac.kr>
Requires-Python: >=3.11
